[
  [
    [
      "sss",
      [
        "#333",
        173.5999755859375,
        124.79998779296875,
        218.39996337890625,
        591.2000244140625,
        0,
        0,
        0
      ],
      [
        "ad2"
      ]
    ],
    [
      "sss1",
      [
        "#000",
        318.4000244140623,
        154.39993286132812,
        187.99998168945314,
        159.6000244140625,
        0,
        0,
        0
      ],
      [
        "ad2"
      ]
    ]
  ],
  [
    [
      "nnnn",
      "const moveAmount = 10;\n\n$(document).keydown(function(event) {\n    let kkk = get_block(\"#sss1\");\n    let currentTop = get_style_id(\"top\", kkk);\n    let currentLeft = get_style_id(\"left\", kkk);\n\n    switch (event.key) {\n        case \"w\":\n            kkk.css(\"top\", currentTop - moveAmount + \"px\");\n            break;\n        case \"s\":\n            kkk.css(\"top\", currentTop + moveAmount + \"px\");\n            break;\n        case \"a\":\n            kkk.css(\"left\", currentLeft - moveAmount + \"px\");\n            break;\n        case \"d\":\n            kkk.css(\"left\", currentLeft + moveAmount + \"px\");\n            break;\n    }\n});"
    ],
    [
      "nnnn1",
      ""
    ]
  ],
  [
    [
      "ad2",
      {
        "background-color": "#555"
      }
    ]
  ],
  [
    100,
    100,
    600,
    "1000",
    "#334",
    0,
    0,
    []
  ]
]